{
  "pluginId": "default",
  "version": "current",
  "label": "Next",
  "banner": null,
  "badge": false,
  "noIndex": false,
  "className": "docs-version-current",
  "isLast": true,
  "docsSidebars": {
    "docsidebar": [
      {
        "type": "category",
        "label": "aml-templates",
        "collapsible": true,
        "collapsed": true,
        "items": [
          {
            "type": "link",
            "label": "Microsoft Open Source Code of Conduct",
            "href": "/documentations/aml-templates/CODE_OF_CONDUCT",
            "docId": "aml-templates/CODE_OF_CONDUCT"
          },
          {
            "type": "link",
            "label": "aml-templates",
            "href": "/documentations/aml-templates/",
            "docId": "aml-templates/README"
          },
          {
            "type": "link",
            "label": "SECURITY",
            "href": "/documentations/aml-templates/SECURITY",
            "docId": "aml-templates/SECURITY"
          },
          {
            "type": "link",
            "label": "aml-templates",
            "href": "/documentations/aml-templates/",
            "docId": "aml-templates/readme"
          }
        ],
        "href": "/documentations/category/aml-templates"
      },
      {
        "type": "link",
        "label": "Caching and Caches",
        "href": "/documentations/caches",
        "docId": "caches"
      },
      {
        "type": "link",
        "label": "documentations",
        "href": "/documentations/",
        "docId": "README"
      },
      {
        "type": "link",
        "label": "sample",
        "href": "/documentations/sample",
        "docId": "sample"
      }
    ]
  },
  "docs": {
    "aml-templates/CODE_OF_CONDUCT": {
      "id": "aml-templates/CODE_OF_CONDUCT",
      "title": "Microsoft Open Source Code of Conduct",
      "description": "This project has adopted the Microsoft Open Source Code of Conduct.",
      "sidebar": "docsidebar"
    },
    "aml-templates/readme": {
      "id": "aml-templates/readme",
      "title": "aml-templates",
      "description": "template repository for azure machine learnings",
      "sidebar": "docsidebar"
    },
    "aml-templates/README": {
      "id": "aml-templates/README",
      "title": "aml-templates",
      "description": "template repository for azure machine learnings",
      "sidebar": "docsidebar"
    },
    "aml-templates/SECURITY": {
      "id": "aml-templates/SECURITY",
      "title": "SECURITY",
      "description": "Security",
      "sidebar": "docsidebar"
    },
    "caches": {
      "id": "caches",
      "title": "caches",
      "description": "When desiging a system , memeory is a very big consideration, becasue this is where everything is stored and processed.",
      "sidebar": "docsidebar"
    },
    "README": {
      "id": "README",
      "title": "documentations",
      "description": "This would be the default documentation page for learning",
      "sidebar": "docsidebar"
    },
    "sample": {
      "id": "sample",
      "title": "sample",
      "description": "Welcome to the page which helps you to learn about various topics",
      "sidebar": "docsidebar"
    }
  }
}